vid2vtf/__init__.py
vid2vtf/__main__.py
vid2vtf/cli.py
vid2vtf/vid2vtf.py
vid2vtf-1.0.8.dist-info/METADATA
vid2vtf-1.0.8.dist-info/WHEEL
vid2vtf-1.0.8.dist-info/entry_points.txt
vid2vtf-1.0.8.dist-info/top_level.txt
vid2vtf-1.0.8.dist-info/RECORD
